autotonne/__init__.py
autotonne/classification.py
autotonne/clustering.py
autotonne/preprocessor.py
autotonne/regression.py
autotonne/reinforcementlearning.py
autotonne/metrics/__init__.py
autotonne/metrics/classification.py
autotonne/models/__init__.py
autotonne/models/classification.py
autotonne/models/model_factory.py
autotonne/models/classification/__init__.py
autotonne/models/classification/adaboost_classifier.py
autotonne/models/classification/catboost_classifier.py
autotonne/models/classification/decisiontree_classifier.py
autotonne/models/classification/extratrees_classifier.py
autotonne/models/classification/gaussianNB_classifier.py
autotonne/models/classification/gaussianprocessclassifier.py
autotonne/models/classification/gradient_boosting_classifier.py
autotonne/models/classification/kneighbors_classifier.py
autotonne/models/classification/lgbm_classifier.py
autotonne/models/classification/lineardiscriminantanalysis.py
autotonne/models/classification/logisticregression.py
autotonne/models/classification/mlpclassifier.py
autotonne/models/classification/quadraticdiscriminantanalysis.py
autotonne/models/classification/randomforest_classifier.py
autotonne/models/classification/ridge_classifier.py
autotonne/models/classification/sgd_classifier.py
autotonne/models/classification/svc_classifier.py
autotonne/models/classification/xgb_classifier.py
autotonne/models/clustering/__init__.py
autotonne/models/clustering/affinitypropagation_cluster.py
autotonne/models/clustering/agglomerativeclustering_cluster.py
autotonne/models/clustering/birch_cluster.py
autotonne/models/clustering/dbscan_cluster.py
autotonne/models/clustering/kmeans_cluster.py
autotonne/models/clustering/kmodes_cluster.py
autotonne/models/clustering/meanshift_cluster.py
autotonne/models/clustering/optics_cluster.py
autotonne/models/clustering/spectral_cluster.py
autotonne/models/regression/__init__.py
autotonne/models/regression/catboost_regressor.py
autotonne/models/regression/elasticnet.py
autotonne-0.0.24.dist-info/LICENSE
autotonne-0.0.24.dist-info/METADATA
autotonne-0.0.24.dist-info/WHEEL
autotonne-0.0.24.dist-info/top_level.txt
autotonne-0.0.24.dist-info/RECORD
